Workbook
Name Slicer_Payment_Method: #N/A
Name Slicer_Status: #N/A

Sheet in
A1: ID | B1: Customer_Name | C1: Order_ID | D1: Order_Date | E1: Product | F1: Category | G1: Quantity | H1: Price | I1: Payment_Method | J1: Status | K1: Total
A2: 100 | B2: Customer_100 | C2: ORD-41285 | D2: 11/22/2024 | E2: Blender | F2: Home | G2: 3 | H2: 38 | I2: Cash on Delivery | J2: Shipped | K2: 114
A3: 101 | B3: Customer_101 | C3: ORD-35783 | D3: 45784 | E3: Smartphone | F3: Electronics | G3: 2 | H3: abd | I3: PayPal | J3: Processing
A4: 102 | B4: Customer_102 | C4: ORD-84355 | D4: 12/23/2024 | E4: Tennis Racket | F4: Sports | G4: 1 | H4: 389.05 | I4: PayPal | J4: Delivered | K4: 389.05
A5: 103 | B5: Customer_103 | C5: ORD-57811 | D5: 3/19/2025 | E5: Science | F5: Books | G5: 5 | H5: 233.92 | I5: PayPal | J5: Processing | K5: 1169.6
A6: 104 | B6: Customer_104 | C6: ORD-93614 | D6: 10/20/2025 | E6: Biography | F6: Books | G6: 1 | H6: 552.51 | I6: Cash on Delivery | J6: Processing | K6: 552.51
A7: 105 | B7: Customer_105 | C7: ORD-22442 | D7: 11/20/2024 | E7: Tennis Racket | F7: Sports | G7: 3 | H7: 122.06 | I7: Cash on Delivery | J7: Cancelled | K7: 366.18
A8: 106 | B8: Customer_106 | C8: ORD-25885 | D8: 45690 | E8: Blender | F8: Home | H8: 978.63 | I8: Bank Transfer | J8: Processing
A9: 107 | B9: Customer_107 | C9: ORD-89122 | D9: 45717 | E9: Biography | F9: Books | G9: 5 | H9: 587.68 | I9: PayPal | J9: Returned | K9: 2938.4
A10: 108 | B10: Customer_108 | C10: ORD-64400 | D10: 10/23/2025 | E10: Science | F10: Books | G10: 1 | H10: 600.29 | I10: Cash on Delivery | J10: Processing | K10: 600.29
A11: 109 | B11: Customer_109 | C11: ORD-18512 | D11: 45721 | E11: Tennis Racket | F11: Sports | G11: 5 | H11: 168.34 | I11: Credit Card | J11: Shipped | K11: 841.7
A12: 110 | B12: Customer_110 | C12: ORD-61020 | D12: 9/26/2025 | E12: Basketball | F12: sports | G12: 5 | H12: four hundred | I12: Cash on Delivery | J12: Cancelled
A13: 111 | B13: Customer_111 | C13: ORD-72349 | D13: 10/22/2025 | E13: Comics | F13: Books | G13: 2 | H13: 865.77 | I13: Credit Card | J13: Returned | K13: 1731.54
A14: 112 | B14: Customer_112 | C14: ORD-80867 | D14: 45691 | E14: Shoes | F14: Clothing | G14: 4 | H14: 752.13 | I14: Bank Transfer | J14: Delivered | K14: 3008.52
A15: 113 | B15: Customer_113 | C15: ORD-23994 | D15: 7/24/2025 | E15: Fiction | F15: Books | G15: 1 | H15: 411.81 | I15: Credit Card | J15: Processing | K15: 411.81
A16: 114 | B16: Customer_114 | C16: ORD-77417 | D16: Jan 5 2023 | E16: Smartphone | F16: Electronics | G16: 2 | H16: 413.13 | I16: Cash on Delivery | J16: Shipped | K16: 826.26
A17: 115 | B17: Customer_115 | C17: ORD-72778 | D17: 45931 | E17: Fiction | F17: Books | G17: 2 | H17: 796.84 | I17: Cash on Delivery | J17: Returned | K17: 1115.576
A18: 116 | B18: Customer_116 | C18: ORD-63660 | D18: 10/30/2025 | E18: Microwave | F18: Home | G18: 4 | I18: Cash on Delivery | J18: Processing
A19: 117 | B19: Customer_117 | C19: ORD-72751 | D19: 45993 | E19: Blender | F19: electronic | G19: -2 | H19: 10000 | I19: Cash on Delivery | J19: Processing | K19: -20000
A20: 118 | B20: Customer_118 | C20: ORD-96061 | D20: 5/31/2025 | E20: Science | F20: Books | G20: 5 | H20: 247.82 | I20: PayPal | J20: Processing | K20: 1239.1
A21: 119 | B21: Customer_119 | C21: ORD-76016 | D21: 12/19/2024 | E21: Basketball | F21: Sports | G21: 4 | H21: 438.19 | I21: Cash on Delivery | J21: Processing | K21: 1752.76
A22: 120 | B22: Customer_120 | C22: ORD-14659 | D22: 6/13/2025 | E22: Yoga Mat | F22: ELECTRONICS | G22: 5 | H22: 300$ | I22: Credit Card | J22: Cancelled
A23: 121 | B23: Customer_121 | C23: ORD-80067 | D23: 45971 | E23: Basketball | F23: Sports | G23: 4 | H23: 523.01 | I23: Credit Card | J23: Delivered | K23: 2092.04
A24: 122 | B24: Customer_122 | C24: ORD-21443 | D24: 5/16/2025 | E24: Microwave | F24: Home | G24: 2 | H24: 556.93 | I24: PayPal | J24: Shipped | K24: 1113.86
A25: 123 | B25: Customer_123 | C25: ORD-11314 | D25: 45818 | E25: Vacuum | F25: electronic | G25: 3 | H25: 615.91 | I25: Cash on Delivery | J25: Cancelled | K25: 1847.73
A26: 124 | B26: Customer_124 | C26: ORD-46136 | D26: 5/31/2025 | E26: Comics | F26: Books | G26: 5 | I26: PayPal | J26: Cancelled
A27: 125 | B27: Customer_125 | C27: ORD-23202 | D27: 45902 | E27: Comics | F27: Books | G27: 4 | H27: 765.69 | I27: PayPal | J27: Shipped | K27: 3062.76
A28: 126 | B28: Customer_126 | C28: ORD-11261 | D28: 5/18/2025 | E28: Shoes | F28: Clothing | G28: 4 | H28: 836.8 | I28: Bank Transfer | J28: Cancelled | K28: 3347.2
A29: 127 | B29: Customer_127 | C29: ORD-65482 | D29: 45996 | E29: Blender | F29: Home | G29: 5 | H29: 336.02 | I29: Bank Transfer | J29: Returned | K29: 1680.1
A30: 128 | B30: Customer_128 | C30: ORD-12270 | D30: 45576 | E30: Lamp | F30: electronics | G30: 3 | H30: 898.69 | I30: Bank Transfer | J30: Delivered | K30: 2696.07
A31: 129 | B31: Customer_129 | C31: ORD-48863 | D31: 6/22/2025 | E31: Science | F31: Books | G31: 4 | H31: 736.71 | I31: Bank Transfer | J31: Returned | K31: 2946.84
A32: 130 | B32: Customer_130 | C32: ORD-34007 | D32: 8/15/2025 | E32: Tennis Racket | F32: Sports | G32: 2 | I32: Bank Transfer | J32: Processing
A33: 131 | B33: Customer_131 | C33: ORD-91396 | D33: 45967 | E33: Lamp | F33: Home | G33: 5 | H33: 616.63 | I33: PayPal | J33: Shipped | K33: 3083.15
A34: 132 | B34: Customer_132 | C34: ORD-40186 | D34: 45692 | E34: Yoga Mat | F34: ELECTRONICS | G34: 1 | H34: 266.7 | I34: PayPal | J34: Delivered | K34: 266.7
A35: 133 | B35: Customer_133 | C35: ORD-68182 | D35: 45424 | E35: Biography | F35: nan | G35: 5 | H35: 343.24 | I35: Credit Card | J35: Shipped | K35: 1716.2
A36: 134 | B36: Customer_134 | C36: ORD-16585 | D36: 45757 | E36: T-shirt | F36: Clothing | G36: -5 | H36: 591.53 | I36: PayPal | J36: Shipped | K36: -2957.65
A37: 135 | B37: Customer_135 | C37: ORD-33656 | D37: 45902 | E37: Smartwatch | F37: electronics | G37: 4 | H37: 446.19 | I37: Cash on Delivery | J37: Cancelled | K37: 1784.76
A38: 136 | B38: Customer_136 | C38: ORD-20985 | D38: 45997 | E38: Headphones | G38: 1 | H38: 696.71 | I38: Credit Card | J38: Delivered | K38: 696.71
A39: 137 | B39: Customer_137 | C39: ORD-91254 | D39: 2/23/2025 | E39: Vacuum | F39: Home | G39: 3 | H39: -100 | I39: Cash on Delivery | J39: Delivered | K39: -300
A40: 138 | B40: Customer_138 | C40: ORD-34319 | D40: 45908 | E40: Lamp | F40: Home | G40: 1 | H40: 531.06 | I40: PayPal | J40: Processing | K40: 531.06
A41: 139 | B41: Customer_139 | C41: ORD-38418 | D41: 45902 | E41: Smartphone | F41: Electronics | G41: 2 | H41: 681.38 | I41: Credit Card | J41: Cancelled | K41: 1362.76
A42: 140 | B42: Customer_140 | C42: ORD-67096 | D42: 2/26/2025 | E42: Fiction | F42: Books | G42: 4 | H42: 588.98 | I42: Credit Card | J42: Returned | K42: 2355.92
A43: 141 | B43: Customer_141 | C43: ORD-45059 | D43: 2/13/2025 | E43: Fiction | F43: Books | G43: 3 | H43: 546.04 | I43: Cash on Delivery | J43: Returned | K43: 1638.12
A44: 142 | B44: Customer_142 | C44: ORD-69018 | D44: 10/30/2025 | E44: Shoes | F44: Clothing | G44: 5 | H44: 645.26 | I44: Credit Card | J44: Shipped | K44: 2258.41
A45: 143 | B45: Customer_143 | C45: ORD-14329 | D45: 45968 | E45: T-shirt | F45: Clothing | G45: 5 | H45: 826.77 | I45: Bank Transfer | J45: Cancelled | K45: 4133.85
A46: 144 | B46: Customer_144 | C46: ORD-89452 | D46: 1/27/2025 | E46: Football | F46: Sports | G46: 5 | H46: 849.07 | I46: Bank Transfer | J46: Processing | K46: 4245.35
A47: 145 | B47: Customer_145 | C47: ORD-75314 | D47: 44931 | E47: Laptop | F47: Electronics | G47: 2 | H47: 860.99 | I47: Bank Transfer | J47: Returned | K47: 1721.98
A48: 146 | B48: Customer_146 | C48: ORD-32755 | D48: 45907 | E48: Basketball | F48: electronic | G48: 2 | H48: 705.42 | I48: Bank Transfer | J48: Processing | K48: 1410.84
A49: 147 | B49: Customer_147 | C49: ORD-80707 | D49: 45662 | E49: Jacket | F49: Clothing | G49: 4 | H49: 596.15 | I49: Cash on Delivery | J49: Shipped | K49: 2384.6
A50: 148 | B50: Customer_148 | C50: ORD-38423 | D50: 3/13/2025 | E50: Tennis Racket | F50: Sports | G50: 1 | H50: 660.98 | I50: Cash on Delivery | J50: Returned | K50: 660.98
A51: 149 | B51: Customer_149 | C51: ORD-95911 | D51: 6/29/2025 | E51: Comics | F51: Books | G51: 5 | H51: 896.38 | I51: Bank Transfer | J51: Cancelled | K51: 4481.9
A52: 150 | B52: Customer_150 | C52: ORD-76902 | D52: 11/27/2024 | E52: Yoga Mat | F52: Sports | G52: 1 | H52: 206.19 | I52: Credit Card | J52: Returned | K52: 206.19
A53: 151 | B53: Customer_151 | C53: ORD-56552 | D53: 45664 | E53: Comics | F53: Books | G53: 2 | H53: 457.16 | I53: PayPal | J53: Processing | K53: 640.024
A54: 152 | B54: Customer_152 | C54: ORD-72869 | D54: 9/22/2025 | E54: Lamp | F54: Home | G54: 3 | H54: 233.11 | I54: PayPal | J54: Returned | K54: 699.33
A55: 153 | B55: Customer_153 | C55: ORD-29721 | D55: 7/16/2025 | E55: Yoga Mat | F55: Sports | G55: 4 | H55: 278.9 | I55: Cash on Delivery | J55: Processing | K55: 1115.6
A56: 154 | B56: Customer_154 | C56: ORD-95990 | D56: 2/21/2025 | E56: Blender | F56: Home | G56: 5 | H56: 789.64 | I56: Cash on Delivery | J56: Cancelled | K56: 3948.2
A57: 155 | B57: Customer_155 | C57: ORD-20182 | D57: 45662 | E57: shoes | F57: Clothing | G57: 1 | H57: 40.95 | I57: PayPal | J57: Returned | K57: 40.95
A58: 156 | B58: Customer_156 | C58: ORD-34679 | D58: 11/28/2024 | E58: Jeans | F58: Clothing | G58: 2 | I58: Bank Transfer | J58: Shipped
A59: 157 | B59: Customer_157 | C59: ORD-34407 | D59: 45819 | E59: Jacket | F59: Clothing | G59: 4 | H59: 275.1 | I59: Bank Transfer | J59: Processing | K59: 1100.4
A60: 158 | B60: Customer_158 | C60: ORD-35817 | D60: 45781 | E60: Smartwatch | F60: Electronics | G60: 1 | H60: 933.58 | I60: Cash on Delivery | J60: Shipped | K60: 933.58
A61: 159 | B61: Customer_159 | C61: ORD-98162 | D61: 7/28/2025 | E61: Microwave | F61: Home | G61: 3 | H61: 163.16 | I61: PayPal | J61: Shipped | K61: 489.48
A62: 160 | B62: Customer_160 | C62: ORD-96037 | D62: 45717 | E62: Science | F62: Books | G62: 5 | H62: 242.52 | I62: Cash on Delivery | J62: Returned | K62: 1212.6
A63: 161 | B63: Customer_161 | C63: ORD-27653 | D63: 12/15/2024 | E63: Science | F63: Books | G63: 4 | H63: 209.32 | I63: Bank Transfer | J63: Shipped | K63: 837.28
A64: 162 | B64: Customer_162 | C64: ORD-27743 | D64: 5/19/2025 | E64: Blender | F64: Home | G64: 2 | H64: 155.76 | I64: Credit Card | J64: Returned | K64: 311.52
A65: 163 | B65: Customer_163 | C65: ORD-24378 | D65: 45047 | E65: Smartwatch | F65: Electronics | G65: 3 | H65: 235.26 | I65: Cash on Delivery | J65: Shipped | K65: 705.78
A66: 164 | B66: Customer_164 | C66: ORD-23010 | D66: 45902 | E66: Tennis Racket | F66: Sports | H66: 587.64 | I66: Credit Card | J66: Returned
A67: 165 | B67: Customer_165 | C67: ORD-55695 | D67: 45515 | E67: Shoes | F67: Clothing | G67: 2 | H67: 443.13 | I67: Credit Card | J67: Delivered | K67: 886.26
A68: 166 | B68: Customer_166 | C68: ORD-97756 | D68: 45723 | E68: T-shirt | F68: electronics | G68: 2 | H68: 569.38 | I68: Cash on Delivery | J68: Shipped | K68: 1138.76
A69: 167 | B69: Customer_167 | C69: ORD-30329 | D69: 45846 | E69: Basketball | F69: Sports | H69: 593.93 | I69: Cash on Delivery | J69: Processing
A70: 168 | B70: Customer_168 | C70: ORD-53430 | D70: 45758 | E70: Biography | F70: Books | G70: 2 | H70: 141.49 | I70: PayPal | J70: Cancelled | K70: 282.98
A71: 169 | B71: Customer_169 | C71: ORD-75539 | D71: 45999 | E71: Basketball | F71: Sports | G71: 1 | H71: 582.13 | I71: Credit Card | J71: Returned | K71: 582.13
A72: 170 | B72: Customer_170 | C72: ORD-21530 | D72: 45726 | E72: Jeans | F72: Clothing | G72: 5 | H72: 741.63 | I72: Bank Transfer | J72: Processing | K72: 3708.15
A73: 171 | B73: Customer_171 | C73: ORD-99790 | D73: 45455 | E73: Shoes | F73: Clothing | G73: 3 | H73: 688.68 | I73: PayPal | J73: Processing | K73: 2066.04
A74: 172 | B74: Customer_172 | C74: ORD-48008 | D74: 11/18/2024 | E74: Comics | F74: Books | G74: 2 | H74: 942.76 | I74: Bank Transfer | J74: Returned | K74: 1885.52
A75: 173 | B75: Customer_173 | C75: ORD-42171 | D75: 45971 | E75: Lamp | F75: Home | G75: 5 | H75: 351.89 | I75: Credit Card | J75: Shipped | K75: 1759.45
A76: 174 | B76: Customer_174 | C76: ORD-16766 | D76: 9/20/2025 | E76: Microwave | F76: ELECTRONICS | G76: 4 | H76: 187.48 | I76: Credit Card | J76: Returned | K76: 749.92
A77: 175 | B77: Customer_175 | C77: ORD-56651 | D77: 2/24/2025 | E77: Headphones | F77: Electronics | G77: 1 | H77: 111.36 | I77: Credit Card | J77: Processing | K77: 111.36
A78: 176 | B78: Customer_176 | C78: ORD-95794 | D78: 7/22/2025 | E78: Comics | F78: Books | G78: 5 | H78: 530.52 | I78: Cash on Delivery | J78: Shipped | K78: 2652.6
A79: 177 | B79: Customer_177 | C79: ORD-64136 | D79: 7/28/2025 | E79: Laptop | F79: Electronics | G79: 1 | H79: 69.48 | I79: Bank Transfer | J79: Returned | K79: 69.48
A80: 178 | B80: Customer_178 | C80: ORD-89906 | D80: 9/18/2025 | E80: Tennis Racket | F80: Sports | G80: 3 | H80: 472.14 | I80: PayPal | J80: Returned | K80: 1416.42
A81: 179 | B81: Customer_179 | C81: ORD-99328 | D81: 45725 | E81: Yoga Mat | F81: Sports | G81: 3 | H81: 868.67 | I81: PayPal | J81: Delivered | K81: 2606.01
A82: 180 | B82: Customer_180 | C82: ORD-86629 | D82: 3/26/2025 | E82: Laptop | G82: 2 | H82: 418.38 | I82: Credit Card | J82: Processing | K82: 836.76
A83: 181 | B83: Customer_181 | C83: ORD-54481 | D83: 12/29/2024 | E83: Smartphone | F83: nan | G83: 1 | H83: 266.48 | I83: Cash on Delivery | J83: Cancelled | K83: 266.48
A84: 182 | B84: Customer_182 | C84: ORD-79672 | D84: 45724 | E84: Shoes | G84: 4 | H84: 538.35 | I84: PayPal | J84: Processing | K84: 2153.4
A85: 183 | B85: Customer_183 | C85: ORD-20916 | D85: 45933 | E85: Shoes | F85: Clothing | G85: 5 | I85: Cash on Delivery | J85: Returned
A86: 184 | B86: Customer_184 | C86: ORD-67799 | D86: 2/15/2025 | E86: Jeans | G86: 4 | H86: 101.19 | I86: Bank Transfer | J86: Processing | K86: 404.76
A87: 185 | B87: Customer_185 | C87: ORD-57123 | D87: 8/14/2025 | E87: Football | F87: Sports | G87: 2 | H87: 730.92 | I87: Cash on Delivery | J87: Cancelled | K87: 1023.288
A88: 186 | B88: Customer_186 | C88: ORD-90569 | D88: 45818 | E88: Laptop | F88: Electronics | G88: 1 | H88: 365.34 | I88: Bank Transfer | J88: Delivered | K88: 365.34
A89: 187 | B89: Customer_187 | C89: ORD-41292 | D89: 11/19/2024 | E89: Smartphone | F89: Electronics | G89: 3 | H89: 882.96 | I89: Bank Transfer | J89: Returned | K89: 2648.88
A90: 188 | B90: Customer_188 | C90: ORD-58590 | D90: 11/19/2024 | E90: Microwave | F90: Home | G90: 5 | H90: 504.05 | I90: Cash on Delivery | J90: Shipped | K90: 2520.25
A91: 189 | B91: Customer_189 | C91: ORD-30627 | D91: 8/14/2025 | E91: Lamp | F91: Home | G91: 1 | H91: 814.68 | I91: Cash on Delivery | J91: Returned | K91: 814.68
A92: 190 | B92: Customer_190 | C92: ORD-38469 | D92: 6/29/2025 | E92: Vacuum | F92: Home | G92: 1 | H92: 920.37 | I92: Bank Transfer | J92: Processing | K92: 920.37
A93: 191 | B93: Customer_191 | C93: ORD-41810 | D93: 7/18/2025 | E93: Fiction | F93: Books | G93: 2 | H93: 881.02 | I93: Cash on Delivery | J93: Returned | K93: 1762.04
A94: 192 | B94: Customer_192 | C94: ORD-35144 | D94: abc | E94: Jacket | F94: Clothing | G94: 4a | H94: 203.63 | I94: Credit Card | J94: Returned
A95: 193 | B95: Customer_193 | C95: ORD-42475 | D95: 45814 | E95: Basketball | H95: 522.02 | I95: PayPal | J95: Shipped
A96: 194 | B96: Customer_194 | C96: ORD-69764 | D96: 45932 | E96: Lamp | F96: Home | G96: 5 | H96: 944.54 | I96: Cash on Delivery | J96: Returned | K96: 4722.7
A97: 195 | B97: Customer_195 | C97: ORD-82876 | D97: 6/19/2025 | E97: Biography | F97: Books | G97: 5 | H97: 817.46 | I97: Cash on Delivery | J97: Returned | K97: 4087.3
A98: 196 | B98: Customer_196 | C98: ORD-78384 | D98: 12/23/2024 | E98: Vacuum | F98: Home | H98: abd | I98: PayPal | J98: Delivered
A99: 197 | B99: Customer_197 | C99: ORD-79139 | D99: 6/23/2025 | E99: Blender | F99: Home | G99: 1 | H99: 160.16 | I99: PayPal | J99: Cancelled | K99: 160.16
A100: 198 | B100: Customer_198 | C100: ORD-14608 | D100: 7/27/2025 | E100: Vacuum | G100: 2 | H100: 497.01 | I100: Cash on Delivery | J100: Shipped | K100: 994.02
...

Sheet clean data
A1: ID | B1: Customer_Name | C1: Order_ID | D1: Order_Date | E1: Product | F1: Category | G1: Quantity | H1: Price | I1: Payment_Method | J1: Status | K1: Total
A2: =in!A2 -> 100 | B2: =TRIM(in!B2) -> Customer_100 | C2: =in!C2 -> ORD-41285 | D2: =IFERROR(DATEVALUE(in!D2),in!D2) -> 11/22/2024 | E2: =PROPER(in!E2) -> Blender | F2: =PROPER(in!F2) -> Home | G2: =in!G2 -> 3 | H2: =IF(ISNUMBER(in!H2),in!H2,"") -> 38 | I2: =IF(in!I2="","unknown",in!I2) -> Cash on Delivery | J2: =in!J2 -> Shipped | K2: =IFERROR(G2*H2,0) -> 114
A3: =in!A3 -> 101 | B3: =TRIM(in!B3) -> Customer_101 | C3: =in!C3 -> ORD-35783 | D3: =IFERROR(DATEVALUE(in!D3),in!D3) -> 45784 | E3: =PROPER(in!E3) -> Smartphone | F3: =PROPER(in!F3) -> Electronics | G3: =in!G3 -> 2 | H3: 0 | I3: =IF(in!I3="","unknown",in!I3) -> PayPal | J3: =in!J3 -> Processing | K3: =IFERROR(G3*H3,0) -> 0
A4: =in!A4 -> 102 | B4: =TRIM(in!B4) -> Customer_102 | C4: =in!C4 -> ORD-84355 | D4: =IFERROR(DATEVALUE(in!D4),in!D4) -> 12/23/2024 | E4: =PROPER(in!E4) -> Tennis Racket | F4: =PROPER(in!F4) -> Sports | G4: =in!G4 -> 1 | H4: =IF(ISNUMBER(in!H4),in!H4,"") -> 389.05 | I4: =IF(in!I4="","unknown",in!I4) -> PayPal | J4: =in!J4 -> Delivered | K4: =IFERROR(G4*H4,0) -> 389.05
A5: =in!A5 -> 103 | B5: =TRIM(in!B5) -> Customer_103 | C5: =in!C5 -> ORD-57811 | D5: =IFERROR(DATEVALUE(in!D5),in!D5) -> 3/19/2025 | E5: =PROPER(in!E5) -> Science | F5: =PROPER(in!F5) -> Books | G5: =in!G5 -> 5 | H5: =IF(ISNUMBER(in!H5),in!H5,"") -> 233.92 | I5: =IF(in!I5="","unknown",in!I5) -> PayPal | J5: =in!J5 -> Processing | K5: =IFERROR(G5*H5,0) -> 1169.6
A6: =in!A6 -> 104 | B6: =TRIM(in!B6) -> Customer_104 | C6: =in!C6 -> ORD-93614 | D6: =IFERROR(DATEVALUE(in!D6),in!D6) -> 10/20/2025 | E6: =PROPER(in!E6) -> Biography | F6: =PROPER(in!F6) -> Books | G6: =in!G6 -> 1 | H6: =IF(ISNUMBER(in!H6),in!H6,"") -> 552.51 | I6: =IF(in!I6="","unknown",in!I6) -> Cash on Delivery | J6: =in!J6 -> Processing | K6: =IFERROR(G6*H6,0) -> 552.51
A7: =in!A7 -> 105 | B7: =TRIM(in!B7) -> Customer_105 | C7: =in!C7 -> ORD-22442 | D7: =IFERROR(DATEVALUE(in!D7),in!D7) -> 11/20/2024 | E7: =PROPER(in!E7) -> Tennis Racket | F7: =PROPER(in!F7) -> Sports | G7: =in!G7 -> 3 | H7: =IF(ISNUMBER(in!H7),in!H7,"") -> 122.06 | I7: =IF(in!I7="","unknown",in!I7) -> Cash on Delivery | J7: =in!J7 -> Cancelled | K7: =IFERROR(G7*H7,0) -> 366.18
A8: =in!A8 -> 106 | B8: =TRIM(in!B8) -> Customer_106 | C8: =in!C8 -> ORD-25885 | D8: =IFERROR(DATEVALUE(in!D8),in!D8) -> 45690 | E8: =PROPER(in!E8) -> Blender | F8: =PROPER(in!F8) -> Home | G8: =in!G8 -> 0 | H8: =IF(ISNUMBER(in!H8),in!H8,"") -> 978.63 | I8: =IF(in!I8="","unknown",in!I8) -> Bank Transfer | J8: =in!J8 -> Processing | K8: =IFERROR(G8*H8,0) -> 0
A9: =in!A9 -> 107 | B9: =TRIM(in!B9) -> Customer_107 | C9: =in!C9 -> ORD-89122 | D9: =IFERROR(DATEVALUE(in!D9),in!D9) -> 45717 | E9: =PROPER(in!E9) -> Biography | F9: =PROPER(in!F9) -> Books | G9: =in!G9 -> 5 | H9: =IF(ISNUMBER(in!H9),in!H9,"") -> 587.68 | I9: =IF(in!I9="","unknown",in!I9) -> PayPal | J9: =in!J9 -> Returned | K9: =IFERROR(G9*H9,0) -> 2938.4
A10: =in!A10 -> 108 | B10: =TRIM(in!B10) -> Customer_108 | C10: =in!C10 -> ORD-64400 | D10: =IFERROR(DATEVALUE(in!D10),in!D10) -> 10/23/2025 | E10: =PROPER(in!E10) -> Science | F10: =PROPER(in!F10) -> Books | G10: =in!G10 -> 1 | H10: =IF(ISNUMBER(in!H10),in!H10,"") -> 600.29 | I10: =IF(in!I10="","unknown",in!I10) -> Cash on Delivery | J10: =in!J10 -> Processing | K10: =IFERROR(G10*H10,0) -> 600.29
A11: =in!A11 -> 109 | B11: =TRIM(in!B11) -> Customer_109 | C11: =in!C11 -> ORD-18512 | D11: =IFERROR(DATEVALUE(in!D11),in!D11) -> 45721 | E11: =PROPER(in!E11) -> Tennis Racket | F11: =PROPER(in!F11) -> Sports | G11: =in!G11 -> 5 | H11: =IF(ISNUMBER(in!H11),in!H11,"") -> 168.34 | I11: =IF(in!I11="","unknown",in!I11) -> Credit Card | J11: =in!J11 -> Shipped | K11: =IFERROR(G11*H11,0) -> 841.7
A12: =in!A12 -> 110 | B12: =TRIM(in!B12) -> Customer_110 | C12: =in!C12 -> ORD-61020 | D12: =IFERROR(DATEVALUE(in!D12),in!D12) -> 9/26/2025 | E12: =PROPER(in!E12) -> Basketball | F12: =PROPER(in!F12) -> Sports | G12: =in!G12 -> 5 | H12: 400 | I12: =IF(in!I12="","unknown",in!I12) -> Cash on Delivery | J12: =in!J12 -> Cancelled | K12: =IFERROR(G12*H12,0) -> 2000
A13: =in!A13 -> 111 | B13: =TRIM(in!B13) -> Customer_111 | C13: =in!C13 -> ORD-72349 | D13: =IFERROR(DATEVALUE(in!D13),in!D13) -> 10/22/2025 | E13: =PROPER(in!E13) -> Comics | F13: =PROPER(in!F13) -> Books | G13: =in!G13 -> 2 | H13: =IF(ISNUMBER(in!H13),in!H13,"") -> 865.77 | I13: =IF(in!I13="","unknown",in!I13) -> Credit Card | J13: =in!J13 -> Returned | K13: =IFERROR(G13*H13,0) -> 1731.54
A14: =in!A14 -> 112 | B14: =TRIM(in!B14) -> Customer_112 | C14: =in!C14 -> ORD-80867 | D14: =IFERROR(DATEVALUE(in!D14),in!D14) -> 45691 | E14: =PROPER(in!E14) -> Shoes | F14: =PROPER(in!F14) -> Clothing | G14: =in!G14 -> 4 | H14: =IF(ISNUMBER(in!H14),in!H14,"") -> 752.13 | I14: =IF(in!I14="","unknown",in!I14) -> Bank Transfer | J14: =in!J14 -> Delivered | K14: =IFERROR(G14*H14,0) -> 3008.52
A15: =in!A15 -> 113 | B15: =TRIM(in!B15) -> Customer_113 | C15: =in!C15 -> ORD-23994 | D15: =IFERROR(DATEVALUE(in!D15),in!D15) -> 7/24/2025 | E15: =PROPER(in!E15) -> Fiction | F15: =PROPER(in!F15) -> Books | G15: =in!G15 -> 1 | H15: =IF(ISNUMBER(in!H15),in!H15,"") -> 411.81 | I15: =IF(in!I15="","unknown",in!I15) -> Credit Card | J15: =in!J15 -> Processing | K15: =IFERROR(G15*H15,0) -> 411.81
A16: =in!A16 -> 114 | B16: =TRIM(in!B16) -> Customer_114 | C16: =in!C16 -> ORD-77417 | D16: 45047 | E16: =PROPER(in!E16) -> Smartphone | F16: =PROPER(in!F16) -> Electronics | G16: =in!G16 -> 2 | H16: =IF(ISNUMBER(in!H16),in!H16,"") -> 413.13 | I16: =IF(in!I16="","unknown",in!I16) -> Cash on Delivery | J16: =in!J16 -> Shipped | K16: =IFERROR(G16*H16,0) -> 826.26
A17: =in!A17 -> 115 | B17: =TRIM(in!B17) -> Customer_115 | C17: =in!C17 -> ORD-72778 | D17: =IFERROR(DATEVALUE(in!D17),in!D17) -> 45931 | E17: =PROPER(in!E17) -> Fiction | F17: =PROPER(in!F17) -> Books | G17: =in!G17 -> 2 | H17: =IF(ISNUMBER(in!H17),in!H17,"") -> 796.84 | I17: =IF(in!I17="","unknown",in!I17) -> Cash on Delivery | J17: =in!J17 -> Returned | K17: =IFERROR(G17*H17,0) -> 1593.68
A18: =in!A18 -> 116 | B18: =TRIM(in!B18) -> Customer_116 | C18: =in!C18 -> ORD-63660 | D18: =IFERROR(DATEVALUE(in!D18),in!D18) -> 10/30/2025 | E18: =PROPER(in!E18) -> Microwave | F18: =PROPER(in!F18) -> Home | G18: =in!G18 -> 4 | H18: 0 | I18: =IF(in!I18="","unknown",in!I18) -> Cash on Delivery | J18: =in!J18 -> Processing | K18: =IFERROR(G18*H18,0) -> 0
A19: =in!A19 -> 117 | B19: =TRIM(in!B19) -> Customer_117 | C19: =in!C19 -> ORD-72751 | D19: =IFERROR(DATEVALUE(in!D19),in!D19) -> 45993 | E19: =PROPER(in!E19) -> Blender | F19: Electronics | G19: 2 | H19: =IF(ISNUMBER(in!H19),in!H19,"") -> 10000 | I19: =IF(in!I19="","unknown",in!I19) -> Cash on Delivery | J19: =in!J19 -> Processing | K19: =IFERROR(G19*H19,0) -> 20000
A20: =in!A20 -> 118 | B20: =TRIM(in!B20) -> Customer_118 | C20: =in!C20 -> ORD-96061 | D20: =IFERROR(DATEVALUE(in!D20),in!D20) -> 5/31/2025 | E20: =PROPER(in!E20) -> Science | F20: =PROPER(in!F20) -> Books | G20: =in!G20 -> 5 | H20: =IF(ISNUMBER(in!H20),in!H20,"") -> 247.82 | I20: =IF(in!I20="","unknown",in!I20) -> PayPal | J20: =in!J20 -> Processing | K20: =IFERROR(G20*H20,0) -> 1239.1
A21: =in!A21 -> 119 | B21: =TRIM(in!B21) -> Customer_119 | C21: =in!C21 -> ORD-76016 | D21: =IFERROR(DATEVALUE(in!D21),in!D21) -> 12/19/2024 | E21: =PROPER(in!E21) -> Basketball | F21: =PROPER(in!F21) -> Sports | G21: =in!G21 -> 4 | H21: =IF(ISNUMBER(in!H21),in!H21,"") -> 438.19 | I21: =IF(in!I21="","unknown",in!I21) -> Cash on Delivery | J21: =in!J21 -> Processing | K21: =IFERROR(G21*H21,0) -> 1752.76
A22: =in!A22 -> 120 | B22: =TRIM(in!B22) -> Customer_120 | C22: =in!C22 -> ORD-14659 | D22: =IFERROR(DATEVALUE(in!D22),in!D22) -> 6/13/2025 | E22: =PROPER(in!E22) -> Yoga Mat | F22: =PROPER(in!F22) -> Electronics | G22: =in!G22 -> 5 | H22: 0 | I22: =IF(in!I22="","unknown",in!I22) -> Credit Card | J22: =in!J22 -> Cancelled | K22: =IFERROR(G22*H22,0) -> 0
A23: =in!A23 -> 121 | B23: =TRIM(in!B23) -> Customer_121 | C23: =in!C23 -> ORD-80067 | D23: =IFERROR(DATEVALUE(in!D23),in!D23) -> 45971 | E23: =PROPER(in!E23) -> Basketball | F23: =PROPER(in!F23) -> Sports | G23: =in!G23 -> 4 | H23: =IF(ISNUMBER(in!H23),in!H23,"") -> 523.01 | I23: =IF(in!I23="","unknown",in!I23) -> Credit Card | J23: =in!J23 -> Delivered | K23: =IFERROR(G23*H23,0) -> 2092.04
A24: =in!A24 -> 122 | B24: =TRIM(in!B24) -> Customer_122 | C24: =in!C24 -> ORD-21443 | D24: =IFERROR(DATEVALUE(in!D24),in!D24) -> 5/16/2025 | E24: =PROPER(in!E24) -> Microwave | F24: =PROPER(in!F24) -> Home | G24: =in!G24 -> 2 | H24: =IF(ISNUMBER(in!H24),in!H24,"") -> 556.93 | I24: =IF(in!I24="","unknown",in!I24) -> PayPal | J24: =in!J24 -> Shipped | K24: =IFERROR(G24*H24,0) -> 1113.86
A25: =in!A25 -> 123 | B25: =TRIM(in!B25) -> Customer_123 | C25: =in!C25 -> ORD-11314 | D25: =IFERROR(DATEVALUE(in!D25),in!D25) -> 45818 | E25: =PROPER(in!E25) -> Vacuum | F25: Electronics | G25: =in!G25 -> 3 | H25: =IF(ISNUMBER(in!H25),in!H25,"") -> 615.91 | I25: =IF(in!I25="","unknown",in!I25) -> Cash on Delivery | J25: =in!J25 -> Cancelled | K25: =IFERROR(G25*H25,0) -> 1847.73
A26: =in!A26 -> 124 | B26: =TRIM(in!B26) -> Customer_124 | C26: =in!C26 -> ORD-46136 | D26: =IFERROR(DATEVALUE(in!D26),in!D26) -> 5/31/2025 | E26: =PROPER(in!E26) -> Comics | F26: =PROPER(in!F26) -> Books | G26: =in!G26 -> 5 | H26: 0 | I26: =IF(in!I26="","unknown",in!I26) -> PayPal | J26: =in!J26 -> Cancelled | K26: =IFERROR(G26*H26,0) -> 0
A27: =in!A27 -> 125 | B27: =TRIM(in!B27) -> Customer_125 | C27: =in!C27 -> ORD-23202 | D27: =IFERROR(DATEVALUE(in!D27),in!D27) -> 45902 | E27: =PROPER(in!E27) -> Comics | F27: =PROPER(in!F27) -> Books | G27: =in!G27 -> 4 | H27: =IF(ISNUMBER(in!H27),in!H27,"") -> 765.69 | I27: =IF(in!I27="","unknown",in!I27) -> PayPal | J27: =in!J27 -> Shipped | K27: =IFERROR(G27*H27,0) -> 3062.76
A28: =in!A28 -> 126 | B28: =TRIM(in!B28) -> Customer_126 | C28: =in!C28 -> ORD-11261 | D28: =IFERROR(DATEVALUE(in!D28),in!D28) -> 5/18/2025 | E28: =PROPER(in!E28) -> Shoes | F28: =PROPER(in!F28) -> Clothing | G28: =in!G28 -> 4 | H28: =IF(ISNUMBER(in!H28),in!H28,"") -> 836.8 | I28: =IF(in!I28="","unknown",in!I28) -> Bank Transfer | J28: =in!J28 -> Cancelled | K28: =IFERROR(G28*H28,0) -> 3347.2
A29: =in!A29 -> 127 | B29: =TRIM(in!B29) -> Customer_127 | C29: =in!C29 -> ORD-65482 | D29: =IFERROR(DATEVALUE(in!D29),in!D29) -> 45996 | E29: =PROPER(in!E29) -> Blender | F29: =PROPER(in!F29) -> Home | G29: =in!G29 -> 5 | H29: =IF(ISNUMBER(in!H29),in!H29,"") -> 336.02 | I29: =IF(in!I29="","unknown",in!I29) -> Bank Transfer | J29: =in!J29 -> Returned | K29: =IFERROR(G29*H29,0) -> 1680.1
A30: =in!A30 -> 128 | B30: =TRIM(in!B30) -> Customer_128 | C30: =in!C30 -> ORD-12270 | D30: =IFERROR(DATEVALUE(in!D30),in!D30) -> 45576 | E30: =PROPER(in!E30) -> Lamp | F30: =PROPER(in!F30) -> Electronics | G30: =in!G30 -> 3 | H30: =IF(ISNUMBER(in!H30),in!H30,"") -> 898.69 | I30: =IF(in!I30="","unknown",in!I30) -> Bank Transfer | J30: =in!J30 -> Delivered | K30: =IFERROR(G30*H30,0) -> 2696.07
A31: =in!A31 -> 129 | B31: =TRIM(in!B31) -> Customer_129 | C31: =in!C31 -> ORD-48863 | D31: =IFERROR(DATEVALUE(in!D31),in!D31) -> 6/22/2025 | E31: =PROPER(in!E31) -> Science | F31: =PROPER(in!F31) -> Books | G31: =in!G31 -> 4 | H31: =IF(ISNUMBER(in!H31),in!H31,"") -> 736.71 | I31: =IF(in!I31="","unknown",in!I31) -> Bank Transfer | J31: =in!J31 -> Returned | K31: =IFERROR(G31*H31,0) -> 2946.84
A32: =in!A32 -> 130 | B32: =TRIM(in!B32) -> Customer_130 | C32: =in!C32 -> ORD-34007 | D32: =IFERROR(DATEVALUE(in!D32),in!D32) -> 8/15/2025 | E32: =PROPER(in!E32) -> Tennis Racket | F32: =PROPER(in!F32) -> Sports | G32: =in!G32 -> 2 | H32: 0 | I32: =IF(in!I32="","unknown",in!I32) -> Bank Transfer | J32: =in!J32 -> Processing | K32: =IFERROR(G32*H32,0) -> 0
A33: =in!A33 -> 131 | B33: =TRIM(in!B33) -> Customer_131 | C33: =in!C33 -> ORD-91396 | D33: =IFERROR(DATEVALUE(in!D33),in!D33) -> 45967 | E33: =PROPER(in!E33) -> Lamp | F33: =PROPER(in!F33) -> Home | G33: =in!G33 -> 5 | H33: =IF(ISNUMBER(in!H33),in!H33,"") -> 616.63 | I33: =IF(in!I33="","unknown",in!I33) -> PayPal | J33: =in!J33 -> Shipped | K33: =IFERROR(G33*H33,0) -> 3083.15
A34: =in!A34 -> 132 | B34: =TRIM(in!B34) -> Customer_132 | C34: =in!C34 -> ORD-40186 | D34: =IFERROR(DATEVALUE(in!D34),in!D34) -> 45692 | E34: =PROPER(in!E34) -> Yoga Mat | F34: =PROPER(in!F34) -> Electronics | G34: =in!G34 -> 1 | H34: =IF(ISNUMBER(in!H34),in!H34,"") -> 266.7 | I34: =IF(in!I34="","unknown",in!I34) -> PayPal | J34: =in!J34 -> Delivered | K34: =IFERROR(G34*H34,0) -> 266.7
A35: =in!A35 -> 133 | B35: =TRIM(in!B35) -> Customer_133 | C35: =in!C35 -> ORD-68182 | D35: =IFERROR(DATEVALUE(in!D35),in!D35) -> 45424 | E35: =PROPER(in!E35) -> Biography | F35: Electronics | G35: =in!G35 -> 5 | H35: =IF(ISNUMBER(in!H35),in!H35,"") -> 343.24 | I35: =IF(in!I35="","unknown",in!I35) -> Credit Card | J35: =in!J35 -> Shipped | K35: =IFERROR(G35*H35,0) -> 1716.2
A36: =in!A36 -> 134 | B36: =TRIM(in!B36) -> Customer_134 | C36: =in!C36 -> ORD-16585 | D36: =IFERROR(DATEVALUE(in!D36),in!D36) -> 45757 | E36: =PROPER(in!E36) -> T-Shirt | F36: =PROPER(in!F36) -> Clothing | G36: 5 | H36: =IF(ISNUMBER(in!H36),in!H36,"") -> 591.53 | I36: =IF(in!I36="","unknown",in!I36) -> PayPal | J36: =in!J36 -> Shipped | K36: =IFERROR(G36*H36,0) -> 2957.65
A37: =in!A37 -> 135 | B37: =TRIM(in!B37) -> Customer_135 | C37: =in!C37 -> ORD-33656 | D37: =IFERROR(DATEVALUE(in!D37),in!D37) -> 45902 | E37: =PROPER(in!E37) -> Smartwatch | F37: =PROPER(in!F37) -> Electronics | G37: =in!G37 -> 4 | H37: =IF(ISNUMBER(in!H37),in!H37,"") -> 446.19 | I37: =IF(in!I37="","unknown",in!I37) -> Cash on Delivery | J37: =in!J37 -> Cancelled | K37: =IFERROR(G37*H37,0) -> 1784.76
A38: =in!A38 -> 136 | B38: =TRIM(in!B38) -> Customer_136 | C38: =in!C38 -> ORD-20985 | D38: =IFERROR(DATEVALUE(in!D38),in!D38) -> 45997 | E38: =PROPER(in!E38) -> Headphones | F38: Electronics | G38: =in!G38 -> 1 | H38: =IF(ISNUMBER(in!H38),in!H38,"") -> 696.71 | I38: =IF(in!I38="","unknown",in!I38) -> Credit Card | J38: =in!J38 -> Delivered | K38: =IFERROR(G38*H38,0) -> 696.71
A39: =in!A39 -> 137 | B39: =TRIM(in!B39) -> Customer_137 | C39: =in!C39 -> ORD-91254 | D39: =IFERROR(DATEVALUE(in!D39),in!D39) -> 2/23/2025 | E39: =PROPER(in!E39) -> Vacuum | F39: =PROPER(in!F39) -> Home | G39: =in!G39 -> 3 | H39: 100 | I39: =IF(in!I39="","unknown",in!I39) -> Cash on Delivery | J39: =in!J39 -> Delivered | K39: =IFERROR(G39*H39,0) -> 300
A40: =in!A40 -> 138 | B40: =TRIM(in!B40) -> Customer_138 | C40: =in!C40 -> ORD-34319 | D40: =IFERROR(DATEVALUE(in!D40),in!D40) -> 45908 | E40: =PROPER(in!E40) -> Lamp | F40: =PROPER(in!F40) -> Home | G40: =in!G40 -> 1 | H40: =IF(ISNUMBER(in!H40),in!H40,"") -> 531.06 | I40: =IF(in!I40="","unknown",in!I40) -> PayPal | J40: =in!J40 -> Processing | K40: =IFERROR(G40*H40,0) -> 531.06
A41: =in!A41 -> 139 | B41: =TRIM(in!B41) -> Customer_139 | C41: =in!C41 -> ORD-38418 | D41: =IFERROR(DATEVALUE(in!D41),in!D41) -> 45902 | E41: =PROPER(in!E41) -> Smartphone | F41: =PROPER(in!F41) -> Electronics | G41: =in!G41 -> 2 | H41: =IF(ISNUMBER(in!H41),in!H41,"") -> 681.38 | I41: =IF(in!I41="","unknown",in!I41) -> Credit Card | J41: =in!J41 -> Cancelled | K41: =IFERROR(G41*H41,0) -> 1362.76
A42: =in!A42 -> 140 | B42: =TRIM(in!B42) -> Customer_140 | C42: =in!C42 -> ORD-67096 | D42: =IFERROR(DATEVALUE(in!D42),in!D42) -> 2/26/2025 | E42: =PROPER(in!E42) -> Fiction | F42: =PROPER(in!F42) -> Books | G42: =in!G42 -> 4 | H42: =IF(ISNUMBER(in!H42),in!H42,"") -> 588.98 | I42: =IF(in!I42="","unknown",in!I42) -> Credit Card | J42: =in!J42 -> Returned | K42: =IFERROR(G42*H42,0) -> 2355.92
A43: =in!A43 -> 141 | B43: =TRIM(in!B43) -> Customer_141 | C43: =in!C43 -> ORD-45059 | D43: =IFERROR(DATEVALUE(in!D43),in!D43) -> 2/13/2025 | E43: =PROPER(in!E43) -> Fiction | F43: =PROPER(in!F43) -> Books | G43: =in!G43 -> 3 | H43: =IF(ISNUMBER(in!H43),in!H43,"") -> 546.04 | I43: =IF(in!I43="","unknown",in!I43) -> Cash on Delivery | J43: =in!J43 -> Returned | K43: =IFERROR(G43*H43,0) -> 1638.12
A44: =in!A44 -> 142 | B44: =TRIM(in!B44) -> Customer_142 | C44: =in!C44 -> ORD-69018 | D44: =IFERROR(DATEVALUE(in!D44),in!D44) -> 10/30/2025 | E44: =PROPER(in!E44) -> Shoes | F44: =PROPER(in!F44) -> Clothing | G44: =in!G44 -> 5 | H44: =IF(ISNUMBER(in!H44),in!H44,"") -> 645.26 | I44: =IF(in!I44="","unknown",in!I44) -> Credit Card | J44: =in!J44 -> Shipped | K44: =IFERROR(G44*H44,0) -> 3226.3
A45: =in!A45 -> 143 | B45: =TRIM(in!B45) -> Customer_143 | C45: =in!C45 -> ORD-14329 | D45: =IFERROR(DATEVALUE(in!D45),in!D45) -> 45968 | E45: =PROPER(in!E45) -> T-Shirt | F45: =PROPER(in!F45) -> Clothing | G45: =in!G45 -> 5 | H45: =IF(ISNUMBER(in!H45),in!H45,"") -> 826.77 | I45: =IF(in!I45="","unknown",in!I45) -> Bank Transfer | J45: =in!J45 -> Cancelled | K45: =IFERROR(G45*H45,0) -> 4133.85
A46: =in!A46 -> 144 | B46: =TRIM(in!B46) -> Customer_144 | C46: =in!C46 -> ORD-89452 | D46: =IFERROR(DATEVALUE(in!D46),in!D46) -> 1/27/2025 | E46: =PROPER(in!E46) -> Football | F46: =PROPER(in!F46) -> Sports | G46: =in!G46 -> 5 | H46: =IF(ISNUMBER(in!H46),in!H46,"") -> 849.07 | I46: =IF(in!I46="","unknown",in!I46) -> Bank Transfer | J46: =in!J46 -> Processing | K46: =IFERROR(G46*H46,0) -> 4245.35
A47: =in!A47 -> 145 | B47: =TRIM(in!B47) -> Customer_145 | C47: =in!C47 -> ORD-75314 | D47: =IFERROR(DATEVALUE(in!D47),in!D47) -> 44931 | E47: =PROPER(in!E47) -> Laptop | F47: =PROPER(in!F47) -> Electronics | G47: =in!G47 -> 2 | H47: =IF(ISNUMBER(in!H47),in!H47,"") -> 860.99 | I47: =IF(in!I47="","unknown",in!I47) -> Bank Transfer | J47: =in!J47 -> Returned | K47: =IFERROR(G47*H47,0) -> 1721.98
A48: =in!A48 -> 146 | B48: =TRIM(in!B48) -> Customer_146 | C48: =in!C48 -> ORD-32755 | D48: =IFERROR(DATEVALUE(in!D48),in!D48) -> 45907 | E48: =PROPER(in!E48) -> Basketball | F48: Electronics | G48: =in!G48 -> 2 | H48: =IF(ISNUMBER(in!H48),in!H48,"") -> 705.42 | I48: =IF(in!I48="","unknown",in!I48) -> Bank Transfer | J48: =in!J48 -> Processing | K48: =IFERROR(G48*H48,0) -> 1410.84
A49: =in!A49 -> 147 | B49: =TRIM(in!B49) -> Customer_147 | C49: =in!C49 -> ORD-80707 | D49: =IFERROR(DATEVALUE(in!D49),in!D49) -> 45662 | E49: =PROPER(in!E49) -> Jacket | F49: =PROPER(in!F49) -> Clothing | G49: =in!G49 -> 4 | H49: =IF(ISNUMBER(in!H49),in!H49,"") -> 596.15 | I49: =IF(in!I49="","unknown",in!I49) -> Cash on Delivery | J49: =in!J49 -> Shipped | K49: =IFERROR(G49*H49,0) -> 2384.6
A50: =in!A50 -> 148 | B50: =TRIM(in!B50) -> Customer_148 | C50: =in!C50 -> ORD-38423 | D50: =IFERROR(DATEVALUE(in!D50),in!D50) -> 3/13/2025 | E50: =PROPER(in!E50) -> Tennis Racket | F50: =PROPER(in!F50) -> Sports | G50: =in!G50 -> 1 | H50: =IF(ISNUMBER(in!H50),in!H50,"") -> 660.98 | I50: =IF(in!I50="","unknown",in!I50) -> Cash on Delivery | J50: =in!J50 -> Returned | K50: =IFERROR(G50*H50,0) -> 660.98
A51: =in!A51 -> 149 | B51: =TRIM(in!B51) -> Customer_149 | C51: =in!C51 -> ORD-95911 | D51: =IFERROR(DATEVALUE(in!D51),in!D51) -> 6/29/2025 | E51: =PROPER(in!E51) -> Comics | F51: =PROPER(in!F51) -> Books | G51: =in!G51 -> 5 | H51: =IF(ISNUMBER(in!H51),in!H51,"") -> 896.38 | I51: =IF(in!I51="","unknown",in!I51) -> Bank Transfer | J51: =in!J51 -> Cancelled | K51: =IFERROR(G51*H51,0) -> 4481.9
A52: =in!A52 -> 150 | B52: =TRIM(in!B52) -> Customer_150 | C52: =in!C52 -> ORD-76902 | D52: =IFERROR(DATEVALUE(in!D52),in!D52) -> 11/27/2024 | E52: =PROPER(in!E52) -> Yoga Mat | F52: =PROPER(in!F52) -> Sports | G52: =in!G52 -> 1 | H52: =IF(ISNUMBER(in!H52),in!H52,"") -> 206.19 | I52: =IF(in!I52="","unknown",in!I52) -> Credit Card | J52: =in!J52 -> Returned | K52: =IFERROR(G52*H52,0) -> 206.19
A53: =in!A53 -> 151 | B53: =TRIM(in!B53) -> Customer_151 | C53: =in!C53 -> ORD-56552 | D53: =IFERROR(DATEVALUE(in!D53),in!D53) -> 45664 | E53: =PROPER(in!E53) -> Comics | F53: =PROPER(in!F53) -> Books | G53: =in!G53 -> 2 | H53: =IF(ISNUMBER(in!H53),in!H53,"") -> 457.16 | I53: =IF(in!I53="","unknown",in!I53) -> PayPal | J53: =in!J53 -> Processing | K53: =IFERROR(G53*H53,0) -> 914.32
A54: =in!A54 -> 152 | B54: =TRIM(in!B54) -> Customer_152 | C54: =in!C54 -> ORD-72869 | D54: =IFERROR(DATEVALUE(in!D54),in!D54) -> 9/22/2025 | E54: =PROPER(in!E54) -> Lamp | F54: =PROPER(in!F54) -> Home | G54: =in!G54 -> 3 | H54: =IF(ISNUMBER(in!H54),in!H54,"") -> 233.11 | I54: =IF(in!I54="","unknown",in!I54) -> PayPal | J54: =in!J54 -> Returned | K54: =IFERROR(G54*H54,0) -> 699.33
A55: =in!A55 -> 153 | B55: =TRIM(in!B55) -> Customer_153 | C55: =in!C55 -> ORD-29721 | D55: =IFERROR(DATEVALUE(in!D55),in!D55) -> 7/16/2025 | E55: =PROPER(in!E55) -> Yoga Mat | F55: =PROPER(in!F55) -> Sports | G55: =in!G55 -> 4 | H55: =IF(ISNUMBER(in!H55),in!H55,"") -> 278.9 | I55: =IF(in!I55="","unknown",in!I55) -> Cash on Delivery | J55: =in!J55 -> Processing | K55: =IFERROR(G55*H55,0) -> 1115.6
A56: =in!A56 -> 154 | B56: =TRIM(in!B56) -> Customer_154 | C56: =in!C56 -> ORD-95990 | D56: =IFERROR(DATEVALUE(in!D56),in!D56) -> 2/21/2025 | E56: =PROPER(in!E56) -> Blender | F56: =PROPER(in!F56) -> Home | G56: =in!G56 -> 5 | H56: =IF(ISNUMBER(in!H56),in!H56,"") -> 789.64 | I56: =IF(in!I56="","unknown",in!I56) -> Cash on Delivery | J56: =in!J56 -> Cancelled | K56: =IFERROR(G56*H56,0) -> 3948.2
A57: =in!A57 -> 155 | B57: =TRIM(in!B57) -> Customer_155 | C57: =in!C57 -> ORD-20182 | D57: =IFERROR(DATEVALUE(in!D57),in!D57) -> 45662 | E57: =PROPER(in!E57) -> Shoes | F57: =PROPER(in!F57) -> Clothing | G57: =in!G57 -> 1 | H57: =IF(ISNUMBER(in!H57),in!H57,"") -> 40.95 | I57: =IF(in!I57="","unknown",in!I57) -> PayPal | J57: =in!J57 -> Returned | K57: =IFERROR(G57*H57,0) -> 40.95
A58: =in!A58 -> 156 | B58: =TRIM(in!B58) -> Customer_156 | C58: =in!C58 -> ORD-34679 | D58: =IFERROR(DATEVALUE(in!D58),in!D58) -> 11/28/2024 | E58: =PROPER(in!E58) -> Jeans | F58: =PROPER(in!F58) -> Clothing | G58: =in!G58 -> 2 | H58: 0 | I58: =IF(in!I58="","unknown",in!I58) -> Bank Transfer | J58: =in!J58 -> Shipped | K58: =IFERROR(G58*H58,0) -> 0
A59: =in!A59 -> 157 | B59: =TRIM(in!B59) -> Customer_157 | C59: =in!C59 -> ORD-34407 | D59: =IFERROR(DATEVALUE(in!D59),in!D59) -> 45819 | E59: =PROPER(in!E59) -> Jacket | F59: =PROPER(in!F59) -> Clothing | G59: =in!G59 -> 4 | H59: =IF(ISNUMBER(in!H59),in!H59,"") -> 275.1 | I59: =IF(in!I59="","unknown",in!I59) -> Bank Transfer | J59: =in!J59 -> Processing | K59: =IFERROR(G59*H59,0) -> 1100.4
A60: =in!A60 -> 158 | B60: =TRIM(in!B60) -> Customer_158 | C60: =in!C60 -> ORD-35817 | D60: =IFERROR(DATEVALUE(in!D60),in!D60) -> 45781 | E60: =PROPER(in!E60) -> Smartwatch | F60: =PROPER(in!F60) -> Electronics | G60: =in!G60 -> 1 | H60: =IF(ISNUMBER(in!H60),in!H60,"") -> 933.58 | I60: =IF(in!I60="","unknown",in!I60) -> Cash on Delivery | J60: =in!J60 -> Shipped | K60: =IFERROR(G60*H60,0) -> 933.58
A61: =in!A61 -> 159 | B61: =TRIM(in!B61) -> Customer_159 | C61: =in!C61 -> ORD-98162 | D61: =IFERROR(DATEVALUE(in!D61),in!D61) -> 7/28/2025 | E61: =PROPER(in!E61) -> Microwave | F61: =PROPER(in!F61) -> Home | G61: =in!G61 -> 3 | H61: =IF(ISNUMBER(in!H61),in!H61,"") -> 163.16 | I61: =IF(in!I61="","unknown",in!I61) -> PayPal | J61: =in!J61 -> Shipped | K61: =IFERROR(G61*H61,0) -> 489.48
A62: =in!A62 -> 160 | B62: =TRIM(in!B62) -> Customer_160 | C62: =in!C62 -> ORD-96037 | D62: =IFERROR(DATEVALUE(in!D62),in!D62) -> 45717 | E62: =PROPER(in!E62) -> Science | F62: =PROPER(in!F62) -> Books | G62: =in!G62 -> 5 | H62: =IF(ISNUMBER(in!H62),in!H62,"") -> 242.52 | I62: =IF(in!I62="","unknown",in!I62) -> Cash on Delivery | J62: =in!J62 -> Returned | K62: =IFERROR(G62*H62,0) -> 1212.6
A63: =in!A63 -> 161 | B63: =TRIM(in!B63) -> Customer_161 | C63: =in!C63 -> ORD-27653 | D63: =IFERROR(DATEVALUE(in!D63),in!D63) -> 12/15/2024 | E63: =PROPER(in!E63) -> Science | F63: =PROPER(in!F63) -> Books | G63: =in!G63 -> 4 | H63: =IF(ISNUMBER(in!H63),in!H63,"") -> 209.32 | I63: =IF(in!I63="","unknown",in!I63) -> Bank Transfer | J63: =in!J63 -> Shipped | K63: =IFERROR(G63*H63,0) -> 837.28
A64: =in!A64 -> 162 | B64: =TRIM(in!B64) -> Customer_162 | C64: =in!C64 -> ORD-27743 | D64: =IFERROR(DATEVALUE(in!D64),in!D64) -> 5/19/2025 | E64: =PROPER(in!E64) -> Blender | F64: =PROPER(in!F64) -> Home | G64: =in!G64 -> 2 | H64: =IF(ISNUMBER(in!H64),in!H64,"") -> 155.76 | I64: =IF(in!I64="","unknown",in!I64) -> Credit Card | J64: =in!J64 -> Returned | K64: =IFERROR(G64*H64,0) -> 311.52
A65: =in!A65 -> 163 | B65: =TRIM(in!B65) -> Customer_163 | C65: =in!C65 -> ORD-24378 | D65: =IFERROR(DATEVALUE(in!D65),in!D65) -> 45047 | E65: =PROPER(in!E65) -> Smartwatch | F65: =PROPER(in!F65) -> Electronics | G65: =in!G65 -> 3 | H65: =IF(ISNUMBER(in!H65),in!H65,"") -> 235.26 | I65: =IF(in!I65="","unknown",in!I65) -> Cash on Delivery | J65: =in!J65 -> Shipped | K65: =IFERROR(G65*H65,0) -> 705.78
A66: =in!A66 -> 164 | B66: =TRIM(in!B66) -> Customer_164 | C66: =in!C66 -> ORD-23010 | D66: =IFERROR(DATEVALUE(in!D66),in!D66) -> 45902 | E66: =PROPER(in!E66) -> Tennis Racket | F66: =PROPER(in!F66) -> Sports | G66: =in!G66 -> 0 | H66: =IF(ISNUMBER(in!H66),in!H66,"") -> 587.64 | I66: =IF(in!I66="","unknown",in!I66) -> Credit Card | J66: =in!J66 -> Returned | K66: =IFERROR(G66*H66,0) -> 0
A67: =in!A67 -> 165 | B67: =TRIM(in!B67) -> Customer_165 | C67: =in!C67 -> ORD-55695 | D67: =IFERROR(DATEVALUE(in!D67),in!D67) -> 45515 | E67: =PROPER(in!E67) -> Shoes | F67: =PROPER(in!F67) -> Clothing | G67: =in!G67 -> 2 | H67: =IF(ISNUMBER(in!H67),in!H67,"") -> 443.13 | I67: =IF(in!I67="","unknown",in!I67) -> Credit Card | J67: =in!J67 -> Delivered | K67: =IFERROR(G67*H67,0) -> 886.26
A68: =in!A68 -> 166 | B68: =TRIM(in!B68) -> Customer_166 | C68: =in!C68 -> ORD-97756 | D68: =IFERROR(DATEVALUE(in!D68),in!D68) -> 45723 | E68: =PROPER(in!E68) -> T-Shirt | F68: =PROPER(in!F68) -> Electronics | G68: =in!G68 -> 2 | H68: =IF(ISNUMBER(in!H68),in!H68,"") -> 569.38 | I68: =IF(in!I68="","unknown",in!I68) -> Cash on Delivery | J68: =in!J68 -> Shipped | K68: =IFERROR(G68*H68,0) -> 1138.76
A69: =in!A69 -> 167 | B69: =TRIM(in!B69) -> Customer_167 | C69: =in!C69 -> ORD-30329 | D69: =IFERROR(DATEVALUE(in!D69),in!D69) -> 45846 | E69: =PROPER(in!E69) -> Basketball | F69: =PROPER(in!F69) -> Sports | G69: =in!G69 -> 0 | H69: =IF(ISNUMBER(in!H69),in!H69,"") -> 593.93 | I69: =IF(in!I69="","unknown",in!I69) -> Cash on Delivery | J69: =in!J69 -> Processing | K69: =IFERROR(G69*H69,0) -> 0
A70: =in!A70 -> 168 | B70: =TRIM(in!B70) -> Customer_168 | C70: =in!C70 -> ORD-53430 | D70: =IFERROR(DATEVALUE(in!D70),in!D70) -> 45758 | E70: =PROPER(in!E70) -> Biography | F70: =PROPER(in!F70) -> Books | G70: =in!G70 -> 2 | H70: =IF(ISNUMBER(in!H70),in!H70,"") -> 141.49 | I70: =IF(in!I70="","unknown",in!I70) -> PayPal | J70: =in!J70 -> Cancelled | K70: =IFERROR(G70*H70,0) -> 282.98
... A81: =in!A81 -> 179 | B81: =TRIM(in!B81) -> Customer_179 | C81: =in!C81 -> ORD-99328 | D81: =IFERROR(DATEVALUE(in!D81),in!D81) -> 45725 | E81: =PROPER(in!E81) -> Yoga Mat | F81: =PROPER(in!F81) -> Sports | G81: =in!G81 -> 3 | H81: =IF(ISNUMBER(in!H81),in!H81,"") -> 868.67 | I81: =IF(in!I81="","unknown",in!I81) -> PayPal | J81: =in!J81 -> Delivered | K81: =IFERROR(G81*H81,0) -> 2606.01
A82: =in!A82 -> 180 | B82: =TRIM(in!B82) -> Customer_180 | C82: =in!C82 -> ORD-86629 | D82: =IFERROR(DATEVALUE(in!D82),in!D82) -> 3/26/2025 | E82: =PROPER(in!E82) -> Laptop | F82: Electronics | G82: =in!G82 -> 2 | H82: =IF(ISNUMBER(in!H82),in!H82,"") -> 418.38 | I82: =IF(in!I82="","unknown",in!I82) -> Credit Card | J82: =in!J82 -> Processing | K82: =IFERROR(G82*H82,0) -> 836.76
A83: =in!A83 -> 181 | B83: =TRIM(in!B83) -> Customer_181 | C83: =in!C83 -> ORD-54481 | D83: =IFERROR(DATEVALUE(in!D83),in!D83) -> 12/29/2024 | E83: =PROPER(in!E83) -> Smartphone | F83: Electronics | G83: =in!G83 -> 1 | H83: =IF(ISNUMBER(in!H83),in!H83,"") -> 266.48 | I83: =IF(in!I83="","unknown",in!I83) -> Cash on Delivery | J83: =in!J83 -> Cancelled | K83: =IFERROR(G83*H83,0) -> 266.48
A84: =in!A84 -> 182 | B84: =TRIM(in!B84) -> Customer_182 | C84: =in!C84 -> ORD-79672 | D84: =IFERROR(DATEVALUE(in!D84),in!D84) -> 45724 | E84: =PROPER(in!E84) -> Shoes | F84: Clothing | G84: =in!G84 -> 4 | H84: =IF(ISNUMBER(in!H84),in!H84,"") -> 538.35 | I84: =IF(in!I84="","unknown",in!I84) -> PayPal | J84: =in!J84 -> Processing | K84: =IFERROR(G84*H84,0) -> 2153.4
A85: =in!A85 -> 183 | B85: =TRIM(in!B85) -> Customer_183 | C85: =in!C85 -> ORD-20916 | D85: =IFERROR(DATEVALUE(in!D85),in!D85) -> 45933 | E85: =PROPER(in!E85) -> Shoes | F85: =PROPER(in!F85) -> Clothing | G85: =in!G85 -> 5 | H85: 0 | I85: =IF(in!I85="","unknown",in!I85) -> Cash on Delivery | J85: =in!J85 -> Returned | K85: =IFERROR(G85*H85,0) -> 0
A86: =in!A86 -> 184 | B86: =TRIM(in!B86) -> Customer_184 | C86: =in!C86 -> ORD-67799 | D86: =IFERROR(DATEVALUE(in!D86),in!D86) -> 2/15/2025 | E86: =PROPER(in!E86) -> Jeans | F86: Clothing | G86: =in!G86 -> 4 | H86: =IF(ISNUMBER(in!H86),in!H86,"") -> 101.19 | I86: =IF(in!I86="","unknown",in!I86) -> Bank Transfer | J86: =in!J86 -> Processing | K86: =IFERROR(G86*H86,0) -> 404.76
A87: =in!A87 -> 185 | B87: =TRIM(in!B87) -> Customer_185 | C87: =in!C87 -> ORD-57123 | D87: =IFERROR(DATEVALUE(in!D87),in!D87) -> 8/14/2025 | E87: =PROPER(in!E87) -> Football | F87: =PROPER(in!F87) -> Sports | G87: =in!G87 -> 2 | H87: =IF(ISNUMBER(in!H87),in!H87,"") -> 730.92 | I87: =IF(in!I87="","unknown",in!I87) -> Cash on Delivery | J87: =in!J87 -> Cancelled | K87: =IFERROR(G87*H87,0) -> 1461.84
A88: =in!A88 -> 186 | B88: =TRIM(in!B88) -> Customer_186 | C88: =in!C88 -> ORD-90569 | D88: =IFERROR(DATEVALUE(in!D88),in!D88) -> 45818 | E88: =PROPER(in!E88) -> Laptop | F88: =PROPER(in!F88) -> Electronics | G88: =in!G88 -> 1 | H88: =IF(ISNUMBER(in!H88),in!H88,"") -> 365.34 | I88: =IF(in!I88="","unknown",in!I88) -> Bank Transfer | J88: =in!J88 -> Delivered | K88: =IFERROR(G88*H88,0) -> 365.34
A89: =in!A89 -> 187 | B89: =TRIM(in!B89) -> Customer_187 | C89: =in!C89 -> ORD-41292 | D89: =IFERROR(DATEVALUE(in!D89),in!D89) -> 11/19/2024 | E89: =PROPER(in!E89) -> Smartphone | F89: =PROPER(in!F89) -> Electronics | G89: =in!G89 -> 3 | H89: =IF(ISNUMBER(in!H89),in!H89,"") -> 882.96 | I89: =IF(in!I89="","unknown",in!I89) -> Bank Transfer | J89: =in!J89 -> Returned | K89: =IFERROR(G89*H89,0) -> 2648.88
A90: =in!A90 -> 188 | B90: =TRIM(in!B90) -> Customer_188 | C90: =in!C90 -> ORD-58590 | D90: =IFERROR(DATEVALUE(in!D90),in!D90) -> 11/19/2024 | E90: =PROPER(in!E90) -> Microwave | F90: =PROPER(in!F90) -> Home | G90: =in!G90 -> 5 | H90: =IF(ISNUMBER(in!H90),in!H90,"") -> 504.05 | I90: =IF(in!I90="","unknown",in!I90) -> Cash on Delivery | J90: =in!J90 -> Shipped | K90: =IFERROR(G90*H90,0) -> 2520.25
A91: =in!A91 -> 189 | B91: =TRIM(in!B91) -> Customer_189 | C91: =in!C91 -> ORD-30627 | D91: =IFERROR(DATEVALUE(in!D91),in!D91) -> 8/14/2025 | E91: =PROPER(in!E91) -> Lamp | F91: =PROPER(in!F91) -> Home | G91: =in!G91 -> 1 | H91: =IF(ISNUMBER(in!H91),in!H91,"") -> 814.68 | I91: =IF(in!I91="","unknown",in!I91) -> Cash on Delivery | J91: =in!J91 -> Returned | K91: =IFERROR(G91*H91,0) -> 814.68
A92: =in!A92 -> 190 | B92: =TRIM(in!B92) -> Customer_190 | C92: =in!C92 -> ORD-38469 | D92: =IFERROR(DATEVALUE(in!D92),in!D92) -> 6/29/2025 | E92: =PROPER(in!E92) -> Vacuum | F92: =PROPER(in!F92) -> Home | G92: =in!G92 -> 1 | H92: =IF(ISNUMBER(in!H92),in!H92,"") -> 920.37 | I92: =IF(in!I92="","unknown",in!I92) -> Bank Transfer | J92: =in!J92 -> Processing | K92: =IFERROR(G92*H92,0) -> 920.37
A93: =in!A93 -> 191 | B93: =TRIM(in!B93) -> Customer_191 | C93: =in!C93 -> ORD-41810 | D93: =IFERROR(DATEVALUE(in!D93),in!D93) -> 7/18/2025 | E93: =PROPER(in!E93) -> Fiction | F93: =PROPER(in!F93) -> Books | G93: =in!G93 -> 2 | H93: =IF(ISNUMBER(in!H93),in!H93,"") -> 881.02 | I93: =IF(in!I93="","unknown",in!I93) -> Cash on Delivery | J93: =in!J93 -> Returned | K93: =IFERROR(G93*H93,0) -> 1762.04
A94: =in!A95 -> 193 | B94: =TRIM(in!B95) -> Customer_193 | C94: =in!C95 -> ORD-42475 | D94: =IFERROR(DATEVALUE(in!D95),in!D95) -> 45814 | E94: =PROPER(in!E95) -> Basketball | F94: Sports | G94: =in!G95 -> 0 | H94: =IF(ISNUMBER(in!H95),in!H95,"") -> 522.02 | I94: =IF(in!I95="","unknown",in!I95) -> PayPal | J94: =in!J95 -> Shipped | K94: =IFERROR(G94*H94,0) -> 0
A95: =in!A96 -> 194 | B95: =TRIM(in!B96) -> Customer_194 | C95: =in!C96 -> ORD-69764 | D95: =IFERROR(DATEVALUE(in!D96),in!D96) -> 45932 | E95: =PROPER(in!E96) -> Lamp | F95: =PROPER(in!F96) -> Home | G95: =in!G96 -> 5 | H95: =IF(ISNUMBER(in!H96),in!H96,"") -> 944.54 | I95: =IF(in!I96="","unknown",in!I96) -> Cash on Delivery | J95: =in!J96 -> Returned | K95: =IFERROR(G95*H95,0) -> 4722.7
A96: =in!A97 -> 195 | B96: =TRIM(in!B97) -> Customer_195 | C96: =in!C97 -> ORD-82876 | D96: =IFERROR(DATEVALUE(in!D97),in!D97) -> 6/19/2025 | E96: =PROPER(in!E97) -> Biography | F96: =PROPER(in!F97) -> Books | G96: =in!G97 -> 5 | H96: =IF(ISNUMBER(in!H97),in!H97,"") -> 817.46 | I96: =IF(in!I97="","unknown",in!I97) -> Cash on Delivery | J96: =in!J97 -> Returned | K96: =IFERROR(G96*H96,0) -> 4087.3
A97: =in!A98 -> 196 | B97: =TRIM(in!B98) -> Customer_196 | C97: =in!C98 -> ORD-78384 | D97: =IFERROR(DATEVALUE(in!D98),in!D98) -> 12/23/2024 | E97: =PROPER(in!E98) -> Vacuum | F97: =PROPER(in!F98) -> Home | G97: =in!G98 -> 0 | H97: 0 | I97: =IF(in!I98="","unknown",in!I98) -> PayPal | J97: =in!J98 -> Delivered | K97: =IFERROR(G97*H97,0) -> 0
A98: =in!A99 -> 197 | B98: =TRIM(in!B99) -> Customer_197 | C98: =in!C99 -> ORD-79139 | D98: =IFERROR(DATEVALUE(in!D99),in!D99) -> 6/23/2025 | E98: =PROPER(in!E99) -> Blender | F98: =PROPER(in!F99) -> Home | G98: =in!G99 -> 1 | H98: =IF(ISNUMBER(in!H99),in!H99,"") -> 160.16 | I98: =IF(in!I99="","unknown",in!I99) -> PayPal | J98: =in!J99 -> Cancelled | K98: =IFERROR(G98*H98,0) -> 160.16
A99: =in!A100 -> 198 | B99: =TRIM(in!B100) -> Customer_198 | C99: =in!C100 -> ORD-14608 | D99: =IFERROR(DATEVALUE(in!D100),in!D100) -> 7/27/2025 | E99: =PROPER(in!E100) -> Vacuum | F99: =PROPER(in!F99) -> Home | G99: =in!G100 -> 2 | H99: =IF(ISNUMBER(in!H100),in!H100,"") -> 497.01 | I99: =IF(in!I100="","unknown",in!I100) -> Cash on Delivery | J99: =in!J100 -> Shipped | K99: =IFERROR(G99*H99,0) -> 994.02
A100: =in!A101 -> 199 | B100: =TRIM(in!B101) -> Customer_199 | C100: =in!C101 -> ORD-82922 | D100: =IFERROR(DATEVALUE(in!D101),in!D101) -> 1/22/2025 | E100: =PROPER(in!E101) -> Blender | F100: =PROPER(in!F101) -> Home | G100: =in!G101 -> 5 | H100: =IF(ISNUMBER(in!H101),in!H101,"") -> 372.28 | I100: =IF(in!I101="","unknown",in!I101) -> Credit Card | J100: =in!J101 -> Shipped | K100: =IFERROR(G100*H100,0) -> 1861.4
A101: =in!A102 -> 175 | B101: =TRIM(in!B102) -> Customer_175 | C101: =in!C102 -> ORD-56651 | D101: =IFERROR(DATEVALUE(in!D102),in!D102) -> 2/24/2025 | E101: =PROPER(in!E102) -> Headphones | F101: =PROPER(in!F102) -> Electronics | G101: =in!G102 -> 1 | H101: =IF(ISNUMBER(in!H102),in!H102,"") -> 111.36 | I101: =IF(in!I102="","unknown",in!I102) -> Credit Card | J101: =in!J102 -> Processing | K101: =IFERROR(G101*H101,0) -> 111.36
A102: =in!A103 -> 142 | B102: =TRIM(in!B103) -> Customer_142 | C102: =in!C103 -> ORD-69018 | D102: =IFERROR(DATEVALUE(in!D103),in!D103) -> 10/30/2025 | E102: =PROPER(in!E103) -> Shoes | F102: =PROPER(in!F103) -> Clothing | G102: =in!G103 -> 5 | H102: =IF(ISNUMBER(in!H103),in!H103,"") -> 645.26 | I102: =IF(in!I103="","unknown",in!I103) -> Credit Card | J102: =in!J103 -> Shipped | K102: =IFERROR(G102*H102,0) -> 3226.3
A103: =in!A104 -> 146 | B103: =TRIM(in!B104) -> Customer_146 | C103: =in!C104 -> ORD-32755 | D103: =IFERROR(DATEVALUE(in!D104),in!D104) -> 45907 | E103: =PROPER(in!E104) -> Basketball | F103: Electronics | G103: =in!G104 -> 2 | H103: =IF(ISNUMBER(in!H104),in!H104,"") -> 705.42 | I103: =IF(in!I104="","unknown",in!I104) -> Bank Transfer | J103: =in!J104 -> Processing | K103: =IFERROR(G103*H103,0) -> 1410.84

Sheet analysis
A3: Category | B3: Sum of Total
A4: Books | B4: 38357.11
A5: Clothing | B5: 32644.38
A6: Electronics | B6: 43678.55
A7: Home | B7: 26023.73
A8: Sports | B8: 19736.25
A9: Grand Total | B9: 160440.02

Sheet analysis 2
A3: Status | B3: Count of Order_ID
A4: Cancelled | B4: 15
A5: Delivered | B5: 11
A6: Processing | B6: 27
A7: Returned | B7: 26
A8: Shipped | B8: 23
A9: Grand Total | B9: 102

Sheet analysis 3
A3: Payment_Method | B3: Sum of Total
A4: Bank Transfer | B4: 43023.67
A5: Cash on Delivery | B5: 64758.3
A6: Credit Card | B6: 25077.63
A7: PayPal | B7: 27580.42
A8: Grand Total | B8: 160440.02

Sheet dashboard
A1: E-Commerce Sales & Operations performance Dashboard
B3: TOTAL REVENUE | E3: TOTAL ORDERS | H3: AVERAGE ORDER VALUE
B4: =SUM('clean data'!K:K) -> 160440.02 | E4: =COUNTA('clean data'!B:B) -> 103 | H4: =B4/E4 -> 1557.6701
